clinique/__init__.py
clinique/feature_engineering.py
clinique-1.3.dist-info/LICENSE.txt
clinique-1.3.dist-info/METADATA
clinique-1.3.dist-info/WHEEL
clinique-1.3.dist-info/top_level.txt
clinique-1.3.dist-info/RECORD
