Metadata-Version: 2.1
Name: clinique
Version: 1.3
Summary: A fantastic package
Home-page: UNKNOWN
Author: aurelien.massiot
Author-email: aurelien.massiot@octo.com
License: MIT
Platform: UNKNOWN
Requires-Dist: pandas
Requires-Dist: numpy
Requires-Dist: scikit-learn
